barbatruc/__init__.py
barbatruc/fd_ns_2d.py
barbatruc/fd_operators.py
barbatruc/fluid_domain.py
barbatruc/lattice.py
barbatruc/examples/__init__.py
barbatruc/examples/cfd_cylinder.py
barbatruc/examples/cfd_lid_driven.py
barbatruc/examples/cfd_poiseuille.py
barbatruc/examples/smurf_test.py
barbatruc-0.1.dist-info/LICENCE.md
barbatruc-0.1.dist-info/METADATA
barbatruc-0.1.dist-info/WHEEL
barbatruc-0.1.dist-info/top_level.txt
barbatruc-0.1.dist-info/RECORD
