Metadata-Version: 2.1
Name: barbatruc
Version: 0.1
Summary: Training computational fluid dynamics solver
Home-page: https://nitrox.cerfacs.fr/open-source/barbatruc
Author: CERFACS-COOP
Author-email: coop@cerfacs.fr
License: CeCILL-B FREE SOFTWARE LICENSE AGREEMENT
Requires-Dist: numpy
Requires-Dist: matplotlib
